barnacle/__init__.py
barnacle/decomposition.py
barnacle/fista.py
barnacle/tensors.py
barnacle/tests/test_decomposition.py
barnacle/tests/test_fista.py
barnacle/tests/test_utils.py
barnacle/utils.py
barnacle-0.1.0.dist-info/LICENSE
barnacle-0.1.0.dist-info/WHEEL
barnacle-0.1.0.dist-info/METADATA
barnacle-0.1.0.dist-info/RECORD
